README.md
setup.cfg
setup.py
fusecry/__init__.py
fusecry/__main__.py
fusecry/_test.py
fusecry/cry.py
fusecry/filesystem.py
fusecry/io.py
fusecry/single.py
fusecry/stream.py
fusecry.egg-info/PKG-INFO
fusecry.egg-info/SOURCES.txt
fusecry.egg-info/dependency_links.txt
fusecry.egg-info/entry_points.txt
fusecry.egg-info/requires.txt
fusecry.egg-info/top_level.txt