Metadata-Version: 1.2
Name: fusecry
Version: 0.11.2
Summary: Encrypted filesystem and encryption tool based on FUSE and AES.
Home-page: https://github.com/nul-one/fusecry
Author: Predrag Mandic
Author-email: github@phlogisto.com
License: BSD
Download-URL: https://github.com/nul-one/fusecry/archive/0.11.2.tar.gz
Platform: UNKNOWN
Requires-Python: >=3.4
